flytekitplugins_bacalhau-1.0.3.post1-py3.8-nspkg.pth
flytekitplugins/bacalhau/__init__.py
flytekitplugins/bacalhau/agent.py
flytekitplugins/bacalhau/task.py
flytekitplugins_bacalhau-1.0.3.post1.dist-info/METADATA
flytekitplugins_bacalhau-1.0.3.post1.dist-info/WHEEL
flytekitplugins_bacalhau-1.0.3.post1.dist-info/namespace_packages.txt
flytekitplugins_bacalhau-1.0.3.post1.dist-info/top_level.txt
flytekitplugins_bacalhau-1.0.3.post1.dist-info/RECORD
